{
    "Header" : {
        "Version": "v0.1",
        "EchoToken": "18393849028490234",
        "Channel":"EXPEDIA",
        "IATA":"0348487"
    },
    "Hotel":"Hotel001",
    "Invetories": [
        {
            "DateRange": {
                "StartDate": "2016-01-01",
                "EndDate": "2016-01-07" // end date is included        
            },
            "RoomType":"STD",
            "RatePlan":"BAR", 
            "DailyInventory":[1,0,4,5,6,2,1,1,1], // could be null
            "LOSInventory":[
                "1,0,4,5,6,2,1", // 2016-01-01 
                "1,0,4,5,6,2,1", // 2016-01-02
                "1,0,4,5,6,2,1",
                "1,0,4,5,6,2,1",
                "1,0,4,5,6,2,1",
                "1,0,4,5,6,2,1",
                "1,0,4,5,6,2,1"
            ]        
        },
        {
            "DateRange": {
                "StartDate": "2016-01-01",
                "EndDate": "2016-01-07" // end date is included        
            },
            "RoomType":"STD",
            "RatePlan":"AP",
            "DailyInventory":[1,0,4,5,6,2,1,1,1],
            "LOSInventory":[  // could be null
                "1,0,4,5,6,2,1", // 2016-01-01
                "1,0,4,5,6,2,1", // 2016-01-02
                "1,0,4,5,6,2,1",
                "1,0,4,5,6,2,1",
                "1,0,4,5,6,2,1",
                "1,0,4,5,6,2,1",
                "1,0,4,5,6,2,1"
            ]        
        }
    ]   
}